opensandbox_mcp/__init__.py
opensandbox_mcp/__main__.py
opensandbox_mcp/py.typed
opensandbox_mcp/server.py
opensandbox_mcp-0.1.0.dist-info/METADATA
opensandbox_mcp-0.1.0.dist-info/WHEEL
opensandbox_mcp-0.1.0.dist-info/entry_points.txt
opensandbox_mcp-0.1.0.dist-info/licenses/LICENSE
opensandbox_mcp-0.1.0.dist-info/RECORD
